{
    "actionOnStepFail": null, 
    "blueprintName": "", 
    "blueprintUuid": "9debd3f3-2142-4991-b1f0-9a6f7a291f1c", 
    "cloneUrl": "", 
    "enabled": true, 
    "externalUuid4": "81ee259d-699d-4341-9c97-f8522a7b298d", 
    "key": "performprecleanuponwindowsworkerlink", 
    "name": "Perform Pre Cleanup on Windows Worker (link)", 
    "parameterMap": [], 
    "projectName": "", 
    "projectUuid": "05c41adc-9b4e-49f9-b72c-aa4ee4a0cf27", 
    "projectVersion": "", 
    "type": "com.servertribe.attune.tuples.StepProjectLinkTuple"
}